ocp/__init__.py
ocp/ocp_darwin_amd64
ocp_darwin_amd64-0.1.9.dist-info/LICENSE
ocp_darwin_amd64-0.1.9.dist-info/METADATA
ocp_darwin_amd64-0.1.9.dist-info/WHEEL
ocp_darwin_amd64-0.1.9.dist-info/top_level.txt
ocp_darwin_amd64-0.1.9.dist-info/RECORD
